MANIFEST.in
README.rst
setup.py
src/dbs/__init__.py
src/dbs.utilitybelt.egg-info/PKG-INFO
src/dbs.utilitybelt.egg-info/SOURCES.txt
src/dbs.utilitybelt.egg-info/dependency_links.txt
src/dbs.utilitybelt.egg-info/namespace_packages.txt
src/dbs.utilitybelt.egg-info/top_level.txt
src/dbs.utilitybelt.egg-info/zip-safe
src/dbs/utilitybelt/__init__.py
src/dbs/utilitybelt/log.py
src/dbs/utilitybelt/utils.py